oci/__init__.py
oci/base_client.py
oci/config.py
oci/constants.py
oci/decorators.py
oci/exceptions.py
oci/fips.py
oci/regions.py
oci/request.py
oci/response.py
oci/service_endpoints.py
oci/signer.py
oci/util.py
oci/version.py
oci/waiter.py
oci/_vendor/__init__.py
oci/_vendor/six.py
oci/_vendor/chardet/__init__.py
oci/_vendor/chardet/big5freq.py
oci/_vendor/chardet/big5prober.py
oci/_vendor/chardet/chardistribution.py
oci/_vendor/chardet/charsetgroupprober.py
oci/_vendor/chardet/charsetprober.py
oci/_vendor/chardet/codingstatemachine.py
oci/_vendor/chardet/compat.py
oci/_vendor/chardet/cp949prober.py
oci/_vendor/chardet/enums.py
oci/_vendor/chardet/escprober.py
oci/_vendor/chardet/escsm.py
oci/_vendor/chardet/eucjpprober.py
oci/_vendor/chardet/euckrfreq.py
oci/_vendor/chardet/euckrprober.py
oci/_vendor/chardet/euctwfreq.py
oci/_vendor/chardet/euctwprober.py
oci/_vendor/chardet/gb2312freq.py
oci/_vendor/chardet/gb2312prober.py
oci/_vendor/chardet/hebrewprober.py
oci/_vendor/chardet/jisfreq.py
oci/_vendor/chardet/jpcntx.py
oci/_vendor/chardet/langbulgarianmodel.py
oci/_vendor/chardet/langcyrillicmodel.py
oci/_vendor/chardet/langgreekmodel.py
oci/_vendor/chardet/langhebrewmodel.py
oci/_vendor/chardet/langhungarianmodel.py
oci/_vendor/chardet/langthaimodel.py
oci/_vendor/chardet/langturkishmodel.py
oci/_vendor/chardet/latin1prober.py
oci/_vendor/chardet/mbcharsetprober.py
oci/_vendor/chardet/mbcsgroupprober.py
oci/_vendor/chardet/mbcssm.py
oci/_vendor/chardet/sbcharsetprober.py
oci/_vendor/chardet/sbcsgroupprober.py
oci/_vendor/chardet/sjisprober.py
oci/_vendor/chardet/universaldetector.py
oci/_vendor/chardet/utf8prober.py
oci/_vendor/chardet/version.py
oci/_vendor/httpsig_cffi/__init__.py
oci/_vendor/httpsig_cffi/requests_auth.py
oci/_vendor/httpsig_cffi/sign.py
oci/_vendor/httpsig_cffi/utils.py
oci/_vendor/httpsig_cffi/verify.py
oci/_vendor/idna/__init__.py
oci/_vendor/idna/codec.py
oci/_vendor/idna/compat.py
oci/_vendor/idna/core.py
oci/_vendor/idna/idnadata.py
oci-2.13.0.dist-info/LICENSE.txt
oci-2.13.0.dist-info/METADATA
oci-2.13.0.dist-info/THIRD_PARTY_LICENSES.txt
oci-2.13.0.dist-info/WHEEL
oci-2.13.0.dist-info/top_level.txt
oci-2.13.0.dist-info/RECORD
