Metadata-Version: 2.1
Name: oci
Version: 2.13.0
Summary: Oracle Cloud Infrastructure Python SDK
Home-page: https://oracle-cloud-infrastructure-python-sdk.readthedocs.io/en/latest/index.html
Author: Oracle
Author-email: joe.levy@oracle.com
License: Universal Permissive License 1.0 or Apache License 2.0
Platform: UNKNOWN
Classifier: Development Status :: 5 - Production/Stable
Classifier: Intended Audience :: Developers
Classifier: License :: OSI Approved :: Apache Software License
Classifier: License :: OSI Approved :: Universal Permissive License (UPL)
Classifier: Programming Language :: Python :: 2.7
Classifier: Programming Language :: Python :: 3.5
Classifier: Programming Language :: Python :: 3.6
Requires-Dist: certifi
Requires-Dist: configparser (==4.0.2)
Requires-Dist: cryptography (==2.8)
Requires-Dist: pyOpenSSL (>=17.5.0)
Requires-Dist: python-dateutil (<3.0.0,>=2.5.3)
Requires-Dist: pytz (>=2016.10)
